MANIFEST.in
README.md
setup.py
apollo/__init__.py
apollo/admin.py
apollo/apps.py
apollo/exceptions.py
apollo/factories.py
apollo/forms.py
apollo/models.py
apollo/settings.py
apollo/signals.py
apollo/urls.py
apollo/views.py
apollo/api/__init__.py
apollo/api/v1/__init__.py
apollo/api/v1/api_views.py
apollo/api/v1/permissions.py
apollo/api/v1/serializers.py
apollo/api/v1/urls.py
apollo/lib/__init__.py
apollo/lib/emails.py
apollo/lib/recaptcha.py
apollo/migrations/0001_initial.py
apollo/migrations/0002_auto_20180214_2053.py
apollo/migrations/0003_externalwebhook_service.py
apollo/migrations/0004_auto_20220816_2013.py
apollo/migrations/0005_alter_apiuser_id_alter_externalwebhook_id_and_more.py
apollo/migrations/0006_formfield_validation_message_and_more.py
apollo/migrations/0007_alter_formfield_default_value_and_more.py
apollo/migrations/0008_alter_formfield_label_alter_formfieldtemplate_label.py
apollo/migrations/0009_formsubmission_created_by.py
apollo/migrations/__init__.py
apollo/static/package-lock.json
apollo/static/package.json
apollo/static/webpack.config.js
apollo/static/build/app.js
apollo/static/images/grid-cell-bg.png
apollo/static/images/logo.png
apollo/static/src/js/vendor/jquery-3.2.1.min.js
apollo/templates/forms_manager.html
apollo/templates/noscript.html
apollo/tests/__init__.py
apollo/tests/test_api.py
apollo/tests/test_forms.py
apollo/tests/test_lib.py
apollo/tests/test_models.py
apollo/tests/test_signals.py
django_apollo_forms.egg-info/PKG-INFO
django_apollo_forms.egg-info/SOURCES.txt
django_apollo_forms.egg-info/dependency_links.txt
django_apollo_forms.egg-info/requires.txt
django_apollo_forms.egg-info/top_level.txt